{
    "rent": [
        {
            "options": "real-estate",
            "date": "10-12-24",
            "images": "/Users/dinhbinh/Dev/my-manager/my-manager/bin/db/real-estate/images/re.r.101224.481",
            "id": "re.r.101224.481",
            "status": "available",
            "provide": "lamdong",
            "district": "dalat",
            "ward": "3",
            "street": "tr\u1ea7n ph\u00fa",
            "type": "rent",
            "categories": "homestay",
            "buildingline": "motorbike",
            "area": 0.0,
            "construction": "1 tr\u1ec7t, 1 l\u1ea7u",
            "function": "1pk, 1 b\u1ebfp, 1pn, 1wc",
            "furniture": "full",
            "legal": false,
            "price": 12.0,
            "description": "- cho thu\u00ea homestay g\u1ed7 , s\u00e2n v\u01b0\u1eddn bbq ngay trung t\u00e2m \u0111\u00e0 l\u1ea1t \n- nh\u00e0 n\u1ed9i th\u1ea5t g\u1ed7 \u1ea5m c\u00fang nh\u01b0 trong h\u00ecn"
        },
        {
            "options": "real-estate",
            "date": "10-12-24",
            "images": "/Users/dinhbinh/Dev/my-manager/my-manager/bin/db/real-estate/images/re.r.101224.440",
            "id": "re.r.101224.440",
            "status": "available",
            "provide": "lamdong",
            "district": "dalat",
            "ward": "1",
            "street": "v\u1ea1n th\u00e0nh",
            "type": "rent",
            "categories": "villa",
            "buildingline": "car",
            "area": 0.0,
            "construction": "1 tr\u1ec7t, 1 l\u1ea7u, 1 \u00e1p",
            "function": "1pk, 1 b\u1ebfp, 6pn, 6wc",
            "furniture": "full",
            "legal": false,
            "price": 25.0,
            "description": "+ di\u1ec7n t\u00edch h\u01a1n 205m2\n+ nh\u00e0 m\u1edbi 100%, s\u00e2n v\u01b0\u1eddn tho\u00e1ng m\u00e1t\n+ \u0111\u1ea7y \u0111\u1ee7 n\u1ed9i th\u1ea5t\n+ \u0111\u01b0\u1eddng xe h\u01a1i v\u00e0o tho\u1ea3i m\u00e1i\n+ v\u1ecb tr\u00ed: g\u1ea7n kdl l\u00e0ng hoa v\u1ea1n th\u00e0nh, th\u00e1c cam ly, kdl fresh garden dalat, g\u1ea7n ch\u1ee3, c\u00e1ch h\u1ed3 xu\u00e2n h\u01b0\u01a1ng 10 ph\u00fat\u2026..\n+ h\u01b0\u1edbng nh\u00e0: t\u00e2y nam\n+ c\u1ecdc 3 th\u00e1ng"
        },
        {
            "options": "real-estate",
            "date": "10-12-24",
            "images": "/Users/dinhbinh/Dev/my-manager/my-manager/bin/db/real-estate/images/re.r.101224.636",
            "id": "re.r.101224.636",
            "status": "available",
            "provide": "lamdong",
            "district": "dalat",
            "ward": "1",
            "street": "phan b\u1ed9i ch\u00e2u",
            "type": "rent",
            "categories": "house",
            "buildingline": "motorbike",
            "area": 0.0,
            "construction": "1 tr\u1ec7t, 1 l\u1ea7u",
            "function": "1pk, 1 b\u1ebfp, 2pn, 3wc",
            "furniture": "full",
            "legal": false,
            "price": 9.5,
            "description": "+ \u0111\u01b0\u1eddng xe m\u00e1y, c\u00f3 ch\u1ed7 \u0111\u1ec3 xe h\u01a1i\n+ \u0111\u1ea7y \u0111\u1ee7 n\u1ed9i th\u1ea5t, v\u00e0o \u1edf ngay\n+ c\u1ecdc 2 \u0111\u00f3ng 1"
        },
        {
            "options": "real-estate",
            "type": "rent",
            "buildingline": "car",
            "categories": "house",
            "description": "+ \u0110\u1ea7y \u0111\u1ee7 n\u1ed9i th\u1ea5t, ch\u1ec9 x\u00e1ch vali v\u00e0o \u1edf\n+ S\u00e2n tr\u01b0\u1edbc \u0111\u1eadu 2 xe \u00f4 t\u00f4 + s\u00e2n sau c\u00f3 h\u1ed3 c\u00e1 s\u00e2n bbq \n+ nh\u00e0 \u0111\u1eb9p, r\u1ed9ng r\u00e3i, th\u00f4ng tho\u00e1ng,view c\u1ef1c \u0111\u1ec9nh\n+ ch\u1ec9 \u1edf h\u1ed9 gia \u0111\u00ecnh, kh\u00f4ng kinh doanh",
            "provide": "lamdong",
            "district": "dalat",
            "ward": "8",
            "street": "Nguy\u1ec5n H\u1eefu C\u1ea3nh",
            "area": "",
            "construction": "1 tr\u1ec7t, 1 l\u1ea7u",
            "function": "1pk, 1 b\u1ebfp, 4pn, 3wc",
            "furniture": "full",
            "legal": "none",
            "price": "13",
            "id": "RE.R.101724.544",
            "date": "10-17-24",
            "status": "available",
            "images": "/Users/dinhbinh/Dev/my-manager/my-manager-v2/bin/db/products/real-estate/images/RE.R.101724.544"
        }
    ],
    "sell": [
        {
            "options": "real-estate",
            "images": "/Users/dinhbinh/Dev/my-manager/my-manager/bin/db/real-estate/images/re.s.100924.5244",
            "id": "re.s.100924.5244",
            "status": "available",
            "provide": "l\u00e2m \u0111\u1ed3ng",
            "district": "\u0111\u00e0 l\u1ea1t",
            "ward": "10",
            "street": "ph\u1ea1m h\u1ed3ng th\u00e1i",
            "type": "sell",
            "categories": "house",
            "buildingline": "car",
            "area": 87.75,
            "construction": "1 h\u1ea7m, 1 tr\u1ec7t, 3 l\u1ea7u",
            "function": "1pk, 1 b\u1ebfp, 5pn, 6wc",
            "furniture": "full",
            "legal": "srxd",
            "price": 14.5,
            "description": "'\n+ nh\u00e0 m\u1edbi, s\u1ea1ch s\u1ebd, g\u1ecdn g\u00e0ng, c\u00f3 h\u1ed3 b\u01a1i\n+ ngang 4.5m\n+ kqh b\u00e0i b\u1ea3n, \u0111\u01b0\u1eddng xe h\u01a1i r\u1ed9ng r\u00e3i\n+ t\u1eb7ng to\u00e0n b\u1ed9 \u0111\u00e1 phong thu\u1ef7 cho ch\u1ee7 m\u1edbi \u1ea1; khu v\u1ef1c y\u00ean t\u0129nh th\u00edch h\u1ee3p ngh\u1ec9 d\u01b0\u1ee1ng"
        },
        {
            "options": "real-estate",
            "images": "/Users/dinhbinh/Dev/my-manager/my-manager/bin/db/real-estate/images/re.s.100924.5244",
            "id": "re.s.100924.123",
            "status": "unavailable",
            "provide": "l\u00e2m \u0111\u1ed3ng",
            "district": "\u0111\u00e0 l\u1ea1t",
            "ward": "11",
            "street": "ph\u1ea1m h\u1ed3ng th\u00e1i",
            "type": "sell",
            "categories": "house",
            "buildingline": "car",
            "area": 87.75,
            "construction": "1 h\u1ea7m, 1 tr\u1ec7t, 3 l\u1ea7u",
            "function": "1pk, 1 b\u1ebfp, 5pn, 6wc",
            "furniture": "full",
            "legal": "srxd",
            "price": 14.5,
            "description": "'\n+ nh\u00e0 m\u1edbi, s\u1ea1ch s\u1ebd, g\u1ecdn g\u00e0ng, c\u00f3 h\u1ed3 b\u01a1i\n+ ngang 4.5m\n+ kqh b\u00e0i b\u1ea3n, \u0111\u01b0\u1eddng xe h\u01a1i r\u1ed9ng r\u00e3i\n+ t\u1eb7ng to\u00e0n b\u1ed9 \u0111\u00e1 phong thu\u1ef7 cho ch\u1ee7 m\u1edbi \u1ea1; khu v\u1ef1c y\u00ean t\u0129nh th\u00edch h\u1ee3p ngh\u1ec9 d\u01b0\u1ee1ng"
        },
        {
            "options": "real-estate",
            "date": "10-12-24",
            "images": "/Users/dinhbinh/Dev/my-manager/my-manager/bin/db/real-estate/images/re.s.101224.2100",
            "id": "re.s.101224.2100",
            "status": "available",
            "provide": "lamdong",
            "district": "dalat",
            "ward": "9",
            "street": "l\u1eef gia",
            "type": "sell",
            "categories": "house",
            "buildingline": "car",
            "area": 112.0,
            "construction": "1 tr\u1ec7t, 2 l\u1ea7u",
            "function": "1pk, 1 b\u1ebfp, 5pn, 5wc",
            "furniture": "full",
            "legal": "srxd",
            "price": 7.8,
            "description": "+ \u0111\u01b0\u1eddng xe h\u01a1i, c\u00f3 s\u00e2n \u0111\u1ec3 xe h\u01a1i\n+ nh\u00e0 m\u1edbi, s\u1ea1ch s\u1ebd, g\u1ecdn g\u00e0ng; c\u00f3 \u0111\u1ea7y \u0111\u1ee7 n\u1ed9i th\u1ea5t"
        },
        {
            "options": "real-estate",
            "date": "10-12-24",
            "images": "/Users/dinhbinh/Dev/my-manager/my-manager/bin/db/real-estate/images/re.s.101224.528",
            "id": "re.s.101224.528",
            "status": "available",
            "provide": "lamdong",
            "district": "dalat",
            "ward": "12",
            "street": "th\u00e1i phi\u00ean",
            "type": "sell",
            "categories": "house",
            "buildingline": "motorbike",
            "area": 54.0,
            "construction": "1 tr\u1ec7t, 2 l\u1ea7u",
            "function": "1pk, 1 b\u1ebfp, 4pn, 3wc",
            "furniture": "basic",
            "legal": "sxdpq",
            "price": 3.6,
            "description": "+ nh\u00e0 m\u1edbi, s\u1ea1ch s\u1ebd, g\u1ecdn g\u00e0ng\n+ c\u00e1ch \u0111\u01b0\u1eddng nh\u1ef1a ch\u00ednh 10m\n- c\u00e1c ti\u1ec7n \u00edch c\u00e1ch nh\u00e0 500m g\u1ed3m: tr\u01b0\u1eddng m\u1ea7m non, tr\u01b0\u1eddng ti\u1ec3u h\u1ecdc, ubnd, c\u00f4ng an, ch\u1ee3, c\u00e2y.  x\u0103ng...\n- c\u0103n nh\u00e0 r\u1ea5t ph\u00f9 h\u1ee3p \u0111\u1ec3 an c\u01b0 l\u00e2u d\u00e0i, ngh\u1ec9 d\u01b0\u1ee1ng, kinh doanh homestay...."
        }
    ],
    "assignment": []
}